pyoxy/__init__.py
pyoxy/api.py
pyoxy/cfg.py
pyoxy/crypto.py
pyoxy/lisk.net
pyoxy/lisk.ntpt
pyoxy/oxy.net
pyoxy/oxy.ntpt
pyoxy/shift.net
pyoxy/shift.ntpt
pyoxy/slots.py
pyoxy/toxy.net
pyoxy/toxy.ntpt
pyoxy/transaction.py
pyoxy/tshift.net
pyoxy/tshift.ntpt
pyoxy/util.py
pyoxy/cli/__init__.py
pyoxy/cli/account.py
pyoxy/cli/delegate.py
pyoxy/cli/network.py
pyoxy/cli/share.py
pyoxy-0.3.data/scripts/pyoxy-cli.py
pyoxy-0.3.dist-info/DESCRIPTION.rst
pyoxy-0.3.dist-info/METADATA
pyoxy-0.3.dist-info/RECORD
pyoxy-0.3.dist-info/WHEEL
pyoxy-0.3.dist-info/metadata.json
pyoxy-0.3.dist-info/top_level.txt
