Metadata-Version: 2.0
Name: pyoxy
Version: 0.3
Summary: .
Home-page: https://github.com/ArkEcosystem/pyoxy
Author: Toons
Author-email: moustikitos@gmail.com
License: Copyright 2017 Toons, MIT licence
Download-URL: https://github.com/ArkEcosystem/pyoxy.git
Keywords: api,Oxycoin
Platform: UNKNOWN
Classifier: Development Status :: 4 - Beta
Classifier: Environment :: Console
Classifier: Environment :: Web Environment
Classifier: Intended Audience :: Developers
Classifier: Intended Audience :: End Users/Desktop
Classifier: License :: OSI Approved :: MIT License
Classifier: Operating System :: OS Independent
Classifier: Programming Language :: Python
Classifier: Programming Language :: Python :: 3
Requires-Dist: docopt
Requires-Dist: pynacl
Requires-Dist: pytz
Requires-Dist: requests
Requires-Dist: yawTtk
